<col:collection xmlns="http://cnx.rice.edu/collxml" xmlns:md="http://cnx.rice.edu/mdml" xmlns:col="http://cnx.rice.edu/collxml" xml:lang="en" type="Course" authors="Srinivas K">
  <metadata xmlns:md="http://cnx.rice.edu/mdml" mdml-version="0.5">
    <md:content-id>col10433</md:content-id>
    <md:title>World events</md:title>
    <md:license url="http://creativecommons.org/licenses/by/2.0/">Creative Commons Attribution License 2.0</md:license>
    <md:language>en</md:language>
    <md:uuid>cacdcec8-b833-4e0d-93cb-546c13dcff50</md:uuid>
<md:slug>world-events</md:slug>
</metadata>
  <col:content>
    <col:subcollection>
      <md:title>afghan war</md:title>
      <col:content>                  </col:content>
    </col:subcollection>
  </col:content>
</col:collection>